cardiac/__init__.py
cardiac/bias_integrals.py
cardiac/fields.py
cardiac/spectrum.py
cardiac/templates.py
cardiac/tracer_spectra.py
cardiac/utils.py
cardiac-1.1.6.dist-info/LICENSE.txt
cardiac-1.1.6.dist-info/METADATA
cardiac-1.1.6.dist-info/WHEEL
cardiac-1.1.6.dist-info/top_level.txt
cardiac-1.1.6.dist-info/RECORD
