Metadata-Version: 2.1
Name: cardiac
Version: 1.1.6
Summary: Code for Anisotropic Redshift Distributions in Angular Clustering
Author-email: Anton Baleato Lizancos <a.baleatolizancos@berkeley.edu>
Project-URL: Homepage, https://github.com/abaleato/CARDiAC
Keywords: feed,reader,tutorial
Classifier: Programming Language :: Python
Classifier: Programming Language :: Python :: 3
Requires-Python: >=3.7
License-File: LICENSE.txt
Requires-Dist: numpy
Requires-Dist: scipy
Requires-Dist: matplotlib
Requires-Dist: astropy
Requires-Dist: healpy
Requires-Dist: py3nj
Requires-Dist: camb
Requires-Dist: numba
